antiplagiarism/__init__.py
antiplagiarism/main.py
antiplagiarism/util.py
antiplagiarism-0.0.15.dist-info/METADATA
antiplagiarism-0.0.15.dist-info/WHEEL
antiplagiarism-0.0.15.dist-info/top_level.txt
antiplagiarism-0.0.15.dist-info/RECORD
