Metadata-Version: 2.1
Name: antiplagiarism
Version: 0.0.15
Summary: antiplagiarism library to detect plagiarism especially on code works
Home-page: https://github.com/riccardobernardi/antiplagiarism
Author: Bernardi Riccardo
Author-email: riccardo.bernardi@rocketmail.com
License: UNKNOWN
Platform: UNKNOWN
Classifier: Programming Language :: Python :: 3
Classifier: License :: OSI Approved :: MIT License
Classifier: Operating System :: OS Independent
Requires-Dist: pygraham
Requires-Dist: numpy
